jedi/__init__.py
jedi_fork-0.1.1.dist-info/METADATA
jedi_fork-0.1.1.dist-info/WHEEL
jedi_fork-0.1.1.dist-info/entry_points.txt
jedi_fork-0.1.1.dist-info/top_level.txt
jedi_fork-0.1.1.dist-info/RECORD
