Metadata-Version: 2.2
Name: jedi-fork
Version: 0.1.1
Summary: Jedi Fork
Author-email: Sebastian <peraltas@seas.upenn.edu>
Requires-Python: >=3.11
